triton_transformer/__init__.py
triton_transformer/autoregressive_wrapper.py
triton_transformer/bmm.py
triton_transformer/cross_entropy.py
triton_transformer/dropout.py
triton_transformer/layernorm.py
triton_transformer/softmax.py
triton_transformer/transformer.py
triton_transformer/utils.py
triton_transformer-0.1.1.dist-info/LICENSE
triton_transformer-0.1.1.dist-info/METADATA
triton_transformer-0.1.1.dist-info/WHEEL
triton_transformer-0.1.1.dist-info/top_level.txt
triton_transformer-0.1.1.dist-info/RECORD
