Metadata-Version: 2.1
Name: triton-transformer
Version: 0.1.1
Summary: Transformer in Triton
Home-page: https://github.com/lucidrains/triton-transformer
Author: Phil Wang
Author-email: lucidrains@gmail.com
License: MIT
Keywords: artificial intelligence,attention mechanism,transformers
Platform: UNKNOWN
Classifier: Development Status :: 4 - Beta
Classifier: Intended Audience :: Developers
Classifier: Topic :: Scientific/Engineering :: Artificial Intelligence
Classifier: License :: OSI Approved :: MIT License
Classifier: Programming Language :: Python :: 3.6
License-File: LICENSE
Requires-Dist: einops
Requires-Dist: torch (>=1.6)
Requires-Dist: triton (==1.0.1.dev20210924)
